Zerodha_Tradehull/Zerodha_Tradehull.py
Zerodha_Tradehull/__init__.py
zerodha_tradehull-1.0.3.dist-info/METADATA
zerodha_tradehull-1.0.3.dist-info/WHEEL
zerodha_tradehull-1.0.3.dist-info/top_level.txt
zerodha_tradehull-1.0.3.dist-info/RECORD
