Metadata-Version: 2.1
Name: Zerodha_Tradehull
Version: 1.0.3
Summary: A Zerodha Codebase from TradeHull
Home-page: https://github.com/TradeHull/Zerodha_Tradehull
Author: TradeHull
Author-email: contact.tradehull@gmail.com
Classifier: Programming Language :: Python :: 3
Classifier: License :: OSI Approved :: MIT License
Classifier: Operating System :: OS Independent
Requires-Python: >=3.8
Requires-Dist: mibian>=0.1.3
Requires-Dist: numpy>=1.24.4
Requires-Dist: pandas>=2.0.3
Requires-Dist: pytz>=2025.1
Requires-Dist: requests>=2.32.3
Requires-Dist: python-socketio>=5.12.1
Requires-Dist: websocket-client>=1.8.0
Requires-Dist: websockets>=13.1
Requires-Dist: chromedriver-autoinstaller>=0.6.4
Requires-Dist: selenium>=4.27.1
Requires-Dist: kiteconnect>=5.0.1
